pink/__init__.py
pink/_pink.cpython-310-x86_64-linux-gnu.so
pink/libCudaLib.so
pink/libPythonBindingLib.so
pink/tools.py
astro_pink-2.5.dist-info/METADATA
astro_pink-2.5.dist-info/WHEEL
astro_pink-2.5.dist-info/entry_points.txt
astro_pink-2.5.dist-info/licenses/LICENSE
astro_pink-2.5.dist-info/RECORD
