Metadata-Version: 2.1
Name: astro-pink
Version: 2.5
Summary: Parallelized rotation and flipping INvariant Kohonen maps
Author-Email: Bernd Doser <bernd.doser@h-its.org>
License: GPL-3.0
Classifier: Development Status :: 5 - Production/Stable
Classifier: License :: OSI Approved :: GNU General Public License v3 (GPLv3)
Classifier: Programming Language :: Python :: 3
Classifier: Topic :: Scientific/Engineering
Classifier: Topic :: Scientific/Engineering :: Mathematics
Classifier: Topic :: Scientific/Engineering :: Artificial Intelligence
Requires-Python: >=3.8
License-File: LICENSE
